ComputMath/__init__.py
ComputMath-1.0.1.dist-info/LICENSE
ComputMath-1.0.1.dist-info/METADATA
ComputMath-1.0.1.dist-info/WHEEL
ComputMath-1.0.1.dist-info/top_level.txt
ComputMath-1.0.1.dist-info/RECORD
