Metadata-Version: 2.1
Name: ComputMath
Version: 1.0.1
Summary: Computational Mathematics Package
Home-page: https://github.com/PopckovS/Computational_Mathematics
Author: Popckov Sergio
Author-email: popckovM10@yandex.ru
License: UNKNOWN
Platform: UNKNOWN
Classifier: Programming Language :: Python :: 3.8
Classifier: License :: OSI Approved :: MIT License
Classifier: Operating System :: Unix
Requires-Python: >=3.6
License-File: LICENSE
